mm_proxy_python_client/__init__.py
mm_proxy_python_client/client.py
mm_proxy_python_client/exceptions.py
mm_proxy_python_client/helpers.py
mm_proxy_python_client/resources/__init__.py
mm_proxy_python_client/resources/mobile_asset.py
mm_proxy_python_client/resources/mobile_consumption.py
mm_proxy_python_client/resources/mobile_data_service.py
mm_proxy_python_client/resources/mobile_limit_consumption_shared_bond.py
mm_proxy_python_client/resources/mobile_network_status.py
mm_proxy_python_client/resources/mobile_roaming.py
mm_proxy_python_client/services/__init__.py
mm_proxy_python_client/services/date.py
mm_proxy_python_client/tests/__init__.py
mm_proxy_python_client/tests/test_client.py
mm_proxy_python_client/tests/resources/__init__.py
mm_proxy_python_client/tests/resources/conftest.py
mm_proxy_python_client/tests/resources/test_mobile_asset.py
mm_proxy_python_client/tests/resources/test_mobile_consumption.py
mm_proxy_python_client/tests/resources/test_mobile_data_service.py
mm_proxy_python_client/tests/resources/test_mobile_limit_consumption_shared_bond.py
mm_proxy_python_client/tests/resources/test_mobile_network_status.py
mm_proxy_python_client/tests/resources/test_mobile_roaming.py
mm_proxy_python_client-0.1.2.dist-info/METADATA
mm_proxy_python_client-0.1.2.dist-info/WHEEL
mm_proxy_python_client-0.1.2.dist-info/top_level.txt
mm_proxy_python_client-0.1.2.dist-info/RECORD
