Metadata-Version: 2.1
Name: mm-proxy-python-client
Version: 0.1.2
Summary: Python wrapper for SomConnexio's MM Proxy (using REST API)
Home-page: https://git.coopdevs.org/coopdevs/som-connexio/masmovil/mm-proxy-python-client
Author: SomConnexió
Author-email: gerard.funosas@somconnexio.coop
Maintainer: Gerard Funosas
License: UNKNOWN
Platform: UNKNOWN
Classifier: Development Status :: 3 - Alpha
Classifier: Operating System :: POSIX :: Linux
Classifier: Programming Language :: Python :: 3
Requires-Dist: requests
